gai/tools/web/mcp_server.py
gai/tools/web/client/__init__.py
gai/tools/web/client/web_client.py
gai/tools/web/lib/__init__.py
gai/tools/web/lib/dtos.py
gai/tools/web/lib/splitters.py
gai_tools_web-0.1.2.dist-info/licenses/LICENSE
gai_tools_web-0.1.2.dist-info/METADATA
gai_tools_web-0.1.2.dist-info/WHEEL
gai_tools_web-0.1.2.dist-info/entry_points.txt
gai_tools_web-0.1.2.dist-info/top_level.txt
gai_tools_web-0.1.2.dist-info/RECORD
