Metadata-Version: 2.4
Name: gai-tools-web
Version: 0.1.2
Author-email: kakkoii1337 <kakkoii1337@gmail.com>
License: MIT License
Requires-Python: >=3.10
License-File: LICENSE
Requires-Dist: gai-lib
Requires-Dist: mcp[cli]>=1.8.1
Provides-Extra: dev
Requires-Dist: gai-lib[dev]>=1.0.218; extra == "dev"
Dynamic: license-file
